{
  "disclaimer": "Exchange rates provided for informational purposes only and do not constitute financial advice of any kind. Although every attempt is made to ensure quality, no guarantees are made of accuracy, validity, availability, or fitness for any purpose. All usage subject to acceptance of Terms: https://openexchangerates.org/terms/",
  "license": "Data sourced from various providers; resale prohibited; no warranties given of any kind. All usage subject to License Agreement: https://openexchangerates.org/license/",
  "timestamp": 1457089210,
  "base": "USD",
  "rates": {
    "AED": 3.672866,
    "AFN": 68.603139,
    "ALL": 126.162,
    "AMD": 490.6,
    "ANG": 1.7883,
    "AOA": 158.8825,
    "ARS": 15.296675,
    "AUD": 1.355983,
    "AWG": 1.791833,
    "AZN": 1.607033,
    "BAM": 1.787775,
    "BBD": 2,
    "BDT": 77.91861,
    "BGN": 1.786039,
    "BHD": 0.376501,
    "BIF": 1548.2925,
    "BMD": 1,
    "BND": 1.387673,
    "BOB": 6.816642,
    "BRL": 3.81597,
    "BSD": 1,
    "BTC": 0.002386902588,
    "BTN": 67.2106,
    "BWP": 11.2467,
    "BYR": 21382.23801,
    "BZD": 1.983455,
    "CAD": 1.343848,
    "CDF": 916.7525,
    "CHF": 0.992909,
    "CLF": 0.024598,
    "CLP": 685.15075,
    "CNY": 6.526175,
    "COP": 3204.21,
    "CRC": 533.7631,
    "CUC": 1,
    "CUP": 0.993258,
    "CVE": 101.09975,
    "CZK": 24.6996,
    "DJF": 177.6995,
    "DKK": 6.810505,
    "DOP": 44.97416,
    "DZD": 108.9142,
    "EEK": 14.31465,
    "EGP": 7.82772,
    "ERN": 15.0015,
    "ETB": 21.237488,
    "EUR": 0.911393,
    "FJD": 2.10585,
    "FKP": 0.707397,
    "GBP": 0.707397,
    "GEL": 2.4694,
    "GGP": 0.707397,
    "GHS": 3.872393,
    "GIP": 0.707397,
    "GMD": 39.492963,
    "GNF": 7639.403864,
    "GTQ": 7.625868,
    "GYD": 203.153167,
    "HKD": 7.766832,
    "HNL": 22.56785,
    "HRK": 6.940279,
    "HTG": 61.34655,
    "HUF": 282.921625,
    "IDR": 13179.5,
    "ILS": 3.898864,
    "IMP": 0.707397,
    "INR": 67.207013,
    "IQD": 1097.3,
    "IRR": 30216.978,
    "ISK": 128.6033,
    "JEP": 0.707397,
    "JMD": 121.32425,
    "JOD": 0.707578,
    "JPY": 113.70425,
    "KES": 101.392388,
    "KGS": 73.019197,
    "KHR": 3999.2325,
    "KMF": 452.611234,
    "KPW": 899.91,
    "KRW": 1209.4675,
    "KWD": 0.29896,
    "KYD": 0.82473,
    "KZT": 344.46375,
    "LAK": 8027.21,
    "LBP": 1503.228333,
    "LKR": 144.04,
    "LRD": 84.66847,
    "LSL": 15.647667,
    "LTL": 3.121917,
    "LVL": 0.642975,
    "LYD": 1.387068,
    "MAD": 9.864303,
    "MDL": 19.90355,
    "MGA": 3212.285,
    "MKD": 56.22875,
    "MMK": 1231.978186,
    "MNT": 2033.25,
    "MOP": 7.964264,
    "MRO": 343.0965,
    "MTL": 0.683602,
    "MUR": 35.849433,
    "MVR": 15.182933,
    "MWK": 730.912725,
    "MXN": 17.921475,
    "MYR": 4.108609,
    "MZN": 48.679868,
    "NAD": 15.628,
    "NGN": 198.789125,
    "NIO": 28.203225,
    "NOK": 8.584553,
    "NPR": 107.481,
    "NZD": 1.481083,
    "OMR": 0.384775,
    "PAB": 1,
    "PEN": 3.473693,
    "PGK": 3.009599,
    "PHP": 46.917663,
    "PKR": 104.5445,
    "PLN": 3.958053,
    "PYG": 5689.3875,
    "QAR": 3.641065,
    "RON": 4.076054,
    "RSD": 112.646275,
    "RUB": 73.330438,
    "RWF": 751.47,
    "SAR": 3.75087,
    "SBD": 8.064234,
    "SCR": 13.164888,
    "SDG": 6.084743,
    "SEK": 8.534479,
    "SGD": 1.384978,
    "SHP": 0.707397,
    "SLL": 4155,
    "SOS": 611.024167,
    "SRD": 3.985399,
    "STD": 22526.24715,
    "SVC": 8.696853,
    "SYP": 219.845,
    "SZL": 15.627125,
    "THB": 35.421088,
    "TJS": 7.870387,
    "TMT": 3.5021,
    "TND": 2.042165,
    "TOP": 2.305469,
    "TRY": 2.917708,
    "TTD": 6.472087,
    "TWD": 32.62543,
    "TZS": 2187.7675,
    "UAH": 26.118625,
    "UGX": 3346.125,
    "USD": 1,
    "UYU": 32.2882,
    "UZS": 2860.7139,
    "VEF": 6.308535,
    "VND": 22313.875,
    "VUV": 112.686667,
    "WST": 2.5189,
    "XAF": 599.720375,
    "XAG": 0.0648,
    "XAU": 0.00079,
    "XCD": 2.69866,
    "XDR": 0.723371,
    "XOF": 602.938275,
    "XPD": 0.00194,
    "XPF": 109.130333,
    "XPT": 0.001061,
    "YER": 214.9128,
    "ZAR": 15.649613,
    "ZMK": 5253.075255,
    "ZMW": 11.378033,
    "ZWL": 322.322775
  }
}