{
  "disclaimer": "Exchange rates provided for informational purposes only and do not constitute financial advice of any kind. Although every attempt is made to ensure quality, no guarantees are made of accuracy, validity, availability, or fitness for any purpose. All usage subject to acceptance of Terms: https://openexchangerates.org/terms/",
  "license": "Data sourced from various providers; resale prohibited; no warranties given of any kind. All usage subject to License Agreement: https://openexchangerates.org/license/",
  "timestamp": 1455192005,
  "base": "USD",
  "rates": {
    "AED": 3.672976,
    "AFN": 68.879999,
    "ALL": 123.006299,
    "AMD": 495.089999,
    "ANG": 1.78875,
    "AOA": 155.545665,
    "ARS": 14.37353,
    "AUD": 1.419988,
    "AWG": 1.793333,
    "AZN": 1.573363,
    "BAM": 1.730556,
    "BBD": 2,
    "BDT": 78.41944,
    "BGN": 1.729669,
    "BHD": 0.377128,
    "BIF": 1558.577476,
    "BMD": 1,
    "BND": 1.389968,
    "BOB": 6.897529,
    "BRL": 3.944906,
    "BSD": 1,
    "BTC": 0.00263679703,
    "BTN": 68.161249,
    "BWP": 11.239488,
    "BYR": 21971.825,
    "BZD": 1.990495,
    "CAD": 1.396824,
    "CDF": 928.216,
    "CHF": 0.971159,
    "CLF": 0.024598,
    "CLP": 714.338706,
    "CNY": 6.573418,
    "COP": 3378.69001,
    "CRC": 535.9297,
    "CUC": 1,
    "CUP": 0.9987,
    "CVE": 97.563334,
    "CZK": 23.92346,
    "DJF": 177.675126,
    "DKK": 6.599388,
    "DOP": 45.57373,
    "DZD": 105.524219,
    "EEK": 13.8597,
    "EGP": 7.830039,
    "ERN": 14.9985,
    "ETB": 21.21314,
    "EUR": 0.883421,
    "FJD": 2.138617,
    "FKP": 0.693191,
    "GBP": 0.693191,
    "GEL": 2.4754,
    "GGP": 0.693191,
    "GHS": 3.959426,
    "GIP": 0.693191,
    "GMD": 39.57956,
    "GNF": 7672.027451,
    "GTQ": 7.639521,
    "GYD": 206.121169,
    "HKD": 7.790243,
    "HNL": 22.52665,
    "HRK": 6.75331,
    "HTG": 59.823762,
    "HUF": 275.844297,
    "IDR": 13477.466667,
    "ILS": 3.886167,
    "IMP": 0.693191,
    "INR": 68.255301,
    "IQD": 1088.549988,
    "IRR": 30191,
    "ISK": 126.48,
    "JEP": 0.693191,
    "JMD": 120.807399,
    "JOD": 0.708844,
    "JPY": 112.1241,
    "KES": 101.8797,
    "KGS": 74.296899,
    "KHR": 4038.624976,
    "KMF": 436.437943,
    "KPW": 899.91,
    "KRW": 1200.354982,
    "KWD": 0.298497,
    "KYD": 0.82339,
    "KZT": 358.90849,
    "LAK": 8154.157403,
    "LBP": 1510.600008,
    "LKR": 143.500099,
    "LRD": 83.830002,
    "LSL": 15.896975,
    "LTL": 3.029411,
    "LVL": 0.621869,
    "LYD": 1.369548,
    "MAD": 9.670682,
    "MDL": 19.8511,
    "MGA": 3157.308333,
    "MKD": 54.4665,
    "MMK": 1226.080025,
    "MNT": 2012.166667,
    "MOP": 8.009176,
    "MRO": 338.787333,
    "MTL": 0.683602,
    "MUR": 35.525763,
    "MVR": 15.32095,
    "MWK": 731.649299,
    "MXN": 19.055,
    "MYR": 4.1379,
    "MZN": 49.3525,
    "NAD": 15.87408,
    "NGN": 198.6708,
    "NIO": 28.04708,
    "NOK": 8.565096,
    "NPR": 108.827,
    "NZD": 1.503525,
    "OMR": 0.384976,
    "PAB": 1,
    "PEN": 3.497912,
    "PGK": 3.0309,
    "PHP": 47.51838,
    "PKR": 104.471301,
    "PLN": 3.927106,
    "PYG": 5803.185,
    "QAR": 3.641175,
    "RON": 3.96202,
    "RSD": 108.628441,
    "RUB": 79.34953,
    "RWF": 752.854369,
    "SAR": 3.750313,
    "SBD": 8.129806,
    "SCR": 13.23499,
    "SDG": 6.084424,
    "SEK": 8.40178,
    "SGD": 1.391079,
    "SHP": 0.693191,
    "SLL": 4098,
    "SOS": 613.165125,
    "SRD": 3.9925,
    "STD": 21897.025,
    "SVC": 8.72485,
    "SYP": 219.778669,
    "SZL": 15.90818,
    "THB": 35.27449,
    "TJS": 7.8373,
    "TMT": 3.501467,
    "TND": 1.999827,
    "TOP": 2.245613,
    "TRY": 2.929175,
    "TTD": 6.445977,
    "TWD": 33.03451,
    "TZS": 2178.446699,
    "UAH": 25.89719,
    "UGX": 3456.536667,
    "USD": 1,
    "UYU": 31.21973,
    "UZS": 2842.185059,
    "VEF": 6.320491,
    "VND": 22254.6,
    "VUV": 113.458751,
    "WST": 2.572017,
    "XAF": 581.480093,
    "XAG": 0.064834,
    "XAU": 0.0008165,
    "XCD": 2.70102,
    "XDR": 0.71173,
    "XOF": 582.587993,
    "XPD": 0.001905,
    "XPF": 105.583851,
    "XPT": 0.001071,
    "YER": 214.9489,
    "ZAR": 15.90661,
    "ZMK": 5252.024745,
    "ZMW": 11.3337,
    "ZWL": 322.387247
  }
}